crazyagent/__init__.py
crazyagent/_response.py
crazyagent/chat.py
crazyagent/memory.py
crazyagent/pretty_prompts.py
crazyagent/utils.py
crazyagent/toolkit/__init__.py
crazyagent/toolkit/_external.py
crazyagent/toolkit/_private.py
crazyagent/toolkit/core.py
crazyagent-1.4.1.dist-info/licenses/LICENSE
crazyagent-1.4.1.dist-info/METADATA
crazyagent-1.4.1.dist-info/WHEEL
crazyagent-1.4.1.dist-info/top_level.txt
crazyagent-1.4.1.dist-info/RECORD
