Metadata-Version: 2.4
Name: crazyagent
Version: 1.4.1
Summary: A minimal, efficient, easy-to-integrate, flexible, and beginner-friendly LLM agent development framework with powerful context management.
Home-page: https://github.com/CrazySand/crazyagent
Author: CrazySand
Author-email: lyt041006@gmail.com
License: MIT
Project-URL: Bug Tracker, https://github.com/CrazySand/crazyagent/issues
Project-URL: Source Code, https://github.com/CrazySand/crazyagent
Platform: any
Classifier: Intended Audience :: Developers
Classifier: Operating System :: OS Independent
Classifier: Programming Language :: Python
Classifier: Programming Language :: Python :: 3
Classifier: Programming Language :: Python :: 3.12
Classifier: Topic :: Software Development :: Libraries
Requires-Python: >=3.10
License-File: LICENSE
Requires-Dist: colorama>=0.4.6
Requires-Dist: typeguard>=4.4.4
Requires-Dist: tabulate>=0.9.0
Requires-Dist: openai>=1.86.0
Requires-Dist: requests>=2.32.3
Requires-Dist: httpx>=0.27.0
Dynamic: author
Dynamic: author-email
Dynamic: classifier
Dynamic: description
Dynamic: description-content-type
Dynamic: home-page
Dynamic: license
Dynamic: license-file
Dynamic: platform
Dynamic: project-url
Dynamic: requires-dist
Dynamic: requires-python
Dynamic: summary
